{
  "actions": [
    {
      "description": "Main intent",
      "name": "MAIN",
      "fulfillment": {
        "conversationName": "BolcomMain"
      },
      "intent": {
        "name": "actions.intent.MAIN",
        "trigger": {
          "queryPatterns": [
            "Bol dot com",
            "buy something from Bol dot com",
            "buy some books",
            "buy some e books"
          ]
        }
      }
    },
    {
      "description": "Buy intent",
      "name": "BUY",
      "fulfillment": {
        "conversationName": "BolcomMain"
      },
      "intent": {
        "name": "bol.intent.BUY",
        "parameters": [{
          "name": "title",
          "type": "BookTitle"
        }],
        "trigger": {
          "queryPatterns": [
            "Order $BookTitle:title",
            "Buy $BookTitle:title"
          ]
        }
      }
    },
    {
      "description": "Horse intent",
      "name": "Horse",
      "fulfillment": {
        "conversationName": "BolcomMain"
      },
      "intent": {
        "name": "bol.intent.HORSE",
        "trigger": {
          "queryPatterns": [
            "Ride a horse"
          ]
        }
      }
    }
  ],
  "conversations": {
    "BolcomMain": {
      "name": "BolcomMain",
      "url": "https://bolcom-gactions.herokuapp.com",
      "fulfillmentApiVersion": 2
    },
    "BolcomBuy": {
      "name": "BolcomBuy",
      "url": "https://bolcom-gactions.herokuapp.com",
      "fulfillmentApiVersion": 2
    },
    "BolcomHorse": {
      "name": "BolcomHorse",
      "url": "https://bolcom-gactions.herokuapp.com",
      "fulfillmentApiVersion": 2
    }
  },
  "types": [
    {
      "name": "BookTitle",
      "entities": [
        {
          "key": "The Lord of the Rings",
          "synonyms": [
            "Lord of the Rings"
          ]
        }
      ],
      "isUserDefined": false
    }
  ]
}
